gmtorch_pse/__init__.py
gmtorch_pse/_gaussian_mixture.py
gmtorch_pse-0.1.2.dev4.dist-info/METADATA
gmtorch_pse-0.1.2.dev4.dist-info/WHEEL
gmtorch_pse-0.1.2.dev4.dist-info/licenses/LICENSE
gmtorch_pse-0.1.2.dev4.dist-info/RECORD
