Metadata-Version: 2.4
Name: gmtorch_pse
Version: 0.1.2.dev4
Summary: A library to work with gm
Project-URL: bugs, https://github.com/msteinle/gmtorch_pse/issues
Project-URL: changelog, https://github.com/msteinle/gmtorch_pse/blob/master/changelog.md
Project-URL: homepage, https://github.com/msteinle/gmtorch_pse
Author-email: Maximilian Steinle <urpyc@student.kit.edu>, Robin Smolenski <ucfip@student.kit.edu>, Michael Wollensak <uzkrl@student.kit.edu>, Sebastian Roll <uzxrk@student.kit.edu>, Gero Paul Maier <ukgye@student.kit.edu>
Maintainer-email: Maximilian Steinle <urpyc@student.kit.edu>, Robin Smolenski <ucfip@student.kit.edu>, Michael Wollensak <uzkrl@student.kit.edu>, Sebastian Roll <uzxrk@student.kit.edu>, Gero Paul Maier <ukgye@student.kit.edu>
License: MIT
License-File: LICENSE
Classifier: License :: OSI Approved :: MIT License
Classifier: Operating System :: OS Independent
Classifier: Programming Language :: Python :: 3
Requires-Python: >=3.10
Provides-Extra: test
Requires-Dist: coverage; extra == 'test'
Requires-Dist: ipdb; extra == 'test'
Requires-Dist: pytest; extra == 'test'
Requires-Dist: ruff; extra == 'test'
Requires-Dist: ty; extra == 'test'
